ACSCeND/__init__.py
ACSCeND/acscend.py
ACSCeND/lr_model.joblib
ACSCeND/lr_scaler.joblib
ACSCeND/model.py
ACSCeND/utils.py
acscend-1.1.dist-info/METADATA
acscend-1.1.dist-info/WHEEL
acscend-1.1.dist-info/top_level.txt
acscend-1.1.dist-info/RECORD
