Metadata-Version: 2.4
Name: ACSCeND
Version: 1.1
Summary: A deep learning tool for bulk RNA-seq deconvolution and Stem Cells Sub-Class prediction.
Home-page: https://github.com/SML-CompBio/ACSCEND
Author: Shreyansh Priyadarshi
Author-email: shreyansh.priyadarshi02@gmail.com
License: BSD 2-clause
Requires-Dist: pandas==2.3.1
Requires-Dist: numpy==2.3.1
Requires-Dist: torch==2.7.1
Requires-Dist: scikit-learn==1.7.0
Requires-Dist: joblib==1.5.1
Requires-Dist: scipy==1.16.0
Dynamic: author
Dynamic: author-email
Dynamic: description
Dynamic: description-content-type
Dynamic: home-page
Dynamic: license
Dynamic: requires-dist
Dynamic: summary
